gspan_mining/__init__.py
gspan_mining/__main__.py
gspan_mining/config.py
gspan_mining/graph.py
gspan_mining/gspan.py
gspan_mining/main.py
gspan_mining-0.2.3.dist-info/METADATA
gspan_mining-0.2.3.dist-info/RECORD
gspan_mining-0.2.3.dist-info/WHEEL
gspan_mining-0.2.3.dist-info/top_level.txt
