Metadata-Version: 2.1
Name: gspan_mining
Version: 0.2.3
Summary: Implementation of frequent subgraph mining algorithm gSpan
Home-page: https://github.com/betterenvi/gSpan
Author: Qingying Chen
Author-email: qychen.pku@gmail.com
License: UNKNOWN
Platform: UNKNOWN
Classifier: Programming Language :: Python :: 2
Classifier: Programming Language :: Python :: 3
Classifier: License :: OSI Approved :: MIT License
Classifier: Operating System :: OS Independent
